[
    {
      "trn": "101053070",
      "RegistrationNo": "SLB-RLOS-131776",
      "RegistrationStatus":"Y",
      "SemesterCost": 204653.13,
      "SemesterNumber": 1,
      "GPA": 2.06,
      "ProductCode": "PAYS",
      "AcademicYear": 2023
    },
    {
      "trn": "117324779",
      "RegistrationNo": "SLB-RLOS-131580",
      "RegistrationStatus":"Y",
      "SemesterCost": 170093.73,
      "SemesterNumber": 1,
      "GPA": 3.84,
      "ProductCode": "PAYS",
      "AcademicYear": 2023
    },
    {
      "trn": "110732120",
      "RegistrationNo": "SLB-RLOS-129449",
      "RegistrationStatus":"Y",
      "SemesterCost": 217571.16,
      "SemesterNumber": 1,
      "GPA": 3.58,
      "ProductCode": "POSTGRAD",
      "AcademicYear": 2023
    },
    {
      "trn": "100291708",
      "RegistrationNo": "SLB-RLOS-123385",
      "RegistrationStatus":"Y",
      "SemesterCost:": 181946.18,
      "SemesterNumber": 1,
      "GPA": 3.79,
      "ProductCode": "",
      "AcademicYear": 2023
    },
    {
      "trn": "101053070",
      "RegistrationNo": "SLB-RLOS-131776",
      "RegistrationStatus":"Y",
      "SemesterCost": 30918.62,
      "Semester": 2,
      "GPA": 0,
      "ProductCode": "",
      "AcademicYear": 2023
    },
    {
      "trn": "117324779",
      "RegistrationNo": "SLB-RLOS-131580",
      "RegistrationStatus":"Y",
      "SemesterCost": 105062.45,
      "SemesterNumber": 2,
      "GPA": 0,
      "ProductCode": "",
      "AcademicYear": 2023
    },
    {
      "trn": "110732120",
      "RegistrationNo": "SLB-RLOS-129449",
      "RegistrationStatus":"Y",
      "SemesterCost": 516608.68,
      "SemesterNumber": 2,
      "GPA": 0,
      "ProductCode": "",
      "AcademicYear": 2023
    }

]